bq_schema_sync/__init__.py
bq_schema_sync/cli.py
bq_schema_sync/schema_sync.py
bq_schema_sync/utils.py
bq_schema_sync-0.2.1.data/data/schemas/example_schema.yaml
tests/__init__.py
tests/test_schema_sync.py
bq_schema_sync-0.2.1.dist-info/LICENSE
bq_schema_sync-0.2.1.dist-info/METADATA
bq_schema_sync-0.2.1.dist-info/WHEEL
bq_schema_sync-0.2.1.dist-info/entry_points.txt
bq_schema_sync-0.2.1.dist-info/top_level.txt
bq_schema_sync-0.2.1.dist-info/RECORD
