Metadata-Version: 2.1
Name: bq-schema-sync
Version: 0.2.1
Summary: A tool to synchronize BigQuery table schemas with local definitions
Home-page: https://github.com/victorelexpe/bq-schema-sync
Author: Victor Hasim Elexpe Ahamri
License: MIT
Project-URL: Documentation, https://github.com/victorelexpe/bq-schema-sync#readme
Project-URL: Source, https://github.com/victorelexpe/bq-schema-sync
Project-URL: Tracker, https://github.com/victorelexpe/bq-schema-sync/issues
Keywords: bigquery schema sync gcp google-cloud
Classifier: Development Status :: 4 - Beta
Classifier: Intended Audience :: Developers
Classifier: License :: OSI Approved :: MIT License
Classifier: Programming Language :: Python :: 3
Classifier: Programming Language :: Python :: 3.8
Classifier: Programming Language :: Python :: 3.9
Classifier: Programming Language :: Python :: 3.10
Classifier: Programming Language :: Python :: 3.11
Classifier: Operating System :: OS Independent
Classifier: Topic :: Software Development :: Libraries :: Python Modules
Classifier: Topic :: Database
Requires-Python: >=3.8
License-File: LICENSE
Requires-Dist: google-cloud-bigquery >=2.0.0
Requires-Dist: google-api-core >=1.22.0
Requires-Dist: pyyaml >=5.0
Provides-Extra: dev
Requires-Dist: check-manifest ; extra == 'dev'
Requires-Dist: flake8 ; extra == 'dev'
Requires-Dist: pytest ; extra == 'dev'
Requires-Dist: black ; extra == 'dev'
Requires-Dist: mypy ; extra == 'dev'
Provides-Extra: docs
Requires-Dist: Sphinx ; extra == 'docs'
Requires-Dist: sphinx-rtd-theme ; extra == 'docs'
Provides-Extra: lint
Requires-Dist: flake8 ; extra == 'lint'
Provides-Extra: test
Requires-Dist: pytest ; extra == 'test'
Provides-Extra: type
Requires-Dist: mypy ; extra == 'type'
